Metadata-Version: 2.1
Name: fs-map
Version: 0.0.1
Summary: Python内置文件和路径处理函数的集合和扩展
Home-page: https://gitee.com/ppbug
Author: Jinghe Li
Author-email: 2981160914@qq.com
License: UNKNOWN
Platform: UNKNOWN
